authplus/__init__.py
authplus/apps.py
authplus/models.py
authplus/py.typed
authplus/urls.py
authplus/locale/hr/LC_MESSAGES/django.mo
authplus/locale/hr/LC_MESSAGES/django.po
authplus/migrations/0001_initial.py
authplus/migrations/__init__.py
authplus/static/authplus/css/login.css
authplus/static/authplus/css/password_change.css
authplus/templates/authplus/auth_base.html
authplus/templates/authplus/login.html
authplus/templates/authplus/logout.html
authplus/templates/authplus/password_change.html
authplus/templates/authplus/password_change_done.html
authplus/templates/authplus/include/auth_titlebar.html
authplus/templates/authplus/include/login_css.html
authplus/templates/authplus/include/login_form.html
authplus/templates/authplus/include/password_change_css.html
authplus/templates/authplus/include/password_change_done.html
authplus/templates/authplus/include/password_change_form.html
authplus/templates/authplus/include/project_css.html
gs_django_authplus-1.0.0.dist-info/METADATA
gs_django_authplus-1.0.0.dist-info/WHEEL
gs_django_authplus-1.0.0.dist-info/licenses/AUTHORS.md
gs_django_authplus-1.0.0.dist-info/licenses/LICENSE
gs_django_authplus-1.0.0.dist-info/RECORD
